{
  "name": "Defender",
  "type": "talent",
  "system": {
    "description": "You are skilled at defending yourself in a fight.",
    "basic": "Successfully Blocking an attack gives you a cumulative +1 to your next Block against the same target, to a maximum of +3.",
    "advanced": "You get one free Block per Round during a fight. This does not count as one of your actions in the Round.",
    "itemModifiers": null,
    "level": 1
  },
  "_id": "GLTTiPXlrmd29AOD",
  "img": "icons/svg/item-bag.svg",
  "effects": [],
  "folder": "o0HgvcRqPlzSZDM3",
  "sort": 2900002,
  "ownership": {
    "default": 0,
    "oo2KG31LDGhYx0MC": 3
  },
  "flags": {},
  "_stats": {
    "compendiumSource": null,
    "duplicateSource": null,
    "coreVersion": "12.331",
    "systemId": "talesoftheoldwest",
    "systemVersion": "0.0.1",
    "createdTime": 1735993094387,
    "modifiedTime": 1735993094387,
    "lastModifiedBy": "oo2KG31LDGhYx0MC"
  },
  "_key": "!items!GLTTiPXlrmd29AOD"
}
